README.md
setup.py
vpnkit
vpnkit.py
VPNKit.egg-info/PKG-INFO
VPNKit.egg-info/SOURCES.txt
VPNKit.egg-info/dependency_links.txt
VPNKit.egg-info/requires.txt
VPNKit.egg-info/top_level.txt