Metadata-Version: 2.1
Name: VPNKit
Version: 0.2.2
Summary: An OpenVPN client
Home-page: UNKNOWN
Author: 54origins
Author-email: opensource@54origins.com
License: UNKNOWN
Platform: UNKNOWN
Classifier: Programming Language :: Python
Classifier: License :: OSI Approved :: MIT License
